pynanostring/__init__.py
pynanostring/__main__.py
pynanostring-0.0.1.dist-info/LICENSE
pynanostring-0.0.1.dist-info/METADATA
pynanostring-0.0.1.dist-info/WHEEL
pynanostring-0.0.1.dist-info/entry_points.txt
pynanostring-0.0.1.dist-info/top_level.txt
pynanostring-0.0.1.dist-info/RECORD
