Metadata-Version: 2.1
Name: pynanostring
Version: 0.0.1
Summary: A bioinformatics package to analyze nanostring data
Home-page: https://github.com/leobiscassi/pynanostring
Author: Léo Biscassi
Author-email: leo.biscassi@gmail.com
License: MIT
Platform: UNKNOWN
Classifier: Programming Language :: Python
Classifier: Programming Language :: Python :: 3
Classifier: Programming Language :: Python :: 3.6
Classifier: Programming Language :: Python :: 3.7
Classifier: Programming Language :: Python :: 3.8
Requires-Dist: pandas
